{"name":"Here I Am!","tagline":"","body":"# Here I Am!\r\n\r\nJust another Web components app.\r\n\r\nShare your position with friends.\r\n\r\n[demo](http://codeland.cz/hereiam/)\r\n\r\n## Requirements\r\n\r\n- webserver\r\n- [PHP](http://php.net/)\r\n- [MySQL](http://www.mysql.com)\r\n- [Composer](https://getcomposer.org/)\r\n- [Bower](http://bower.io/)\r\n\r\n## Installation\r\n\r\n> git clone https://github.com/codelandcz/hereiam.git\r\n\r\n> composer install\r\n\r\n> bower install\r\n\r\nPrepare your database:\r\n\r\n    CREATE TABLE position (\r\n      `name` varchar(16) NOT NULL,\r\n      lat double NOT NULL,\r\n      lng double NOT NULL,\r\n      `time` timestamp NOT NULL DEFAULT CURRENT_TIMESTAMP,\r\n      UNIQUE KEY `name` (`name`)\r\n    ) ENGINE=InnoDB DEFAULT CHARSET=latin1;\r\n\r\nMake you own configuration:\r\ncreate new file config.yml by making a copy of [config.yml.dist](src/config.yml.dist).\r\n\r\n## Run\r\nPoint your webserver to the cloned directory and start your browser.\r\n\r\n## Usage\r\nUser is requested for his name and position. Map is refreshed with his position in the center. Map shows positions of all users.\r\n\r\nUser can refresh the positions by a refresh button.\r\n","google":"","note":"Don't delete this file! It's used internally to help with page regeneration."}